Workbook

Sheet Como usar
A1: Controle Financeiro Privado: planilha
A2: A mesma ideia do aplicativo, em planilha. Seus dados ficam só na sua conta do Google.
A4: Passo a passo
A5: 1. Abra a aba "Resumo" e digite seu saldo inicial (a célula amarela).
A6: 2. Na aba "Lançamentos", escreva uma linha para cada entrada ou saída. As células amarelas são suas; as azuis são calculadas.
A7: - Situação "Já aconteceu" mexe no saldo. "Vai acontecer" é conta ou entrada prevista (aluguel, salário...).
A8: - Importância: Essencial, Dívidas, Importante ou Quero (o que é desejo).
A9: 3. A aba "Resumo" mostra o saldo, o saldo livre até o fim do mês e quanto da renda vai para dívidas e parcelas.
A10: 4. A aba "A pagar" lista o que vai vencer, da maior importância para a menor ("Em que ordem pagar?").
A11: 5. Antes de uma compra grande, use a aba "Simulador". Ela mostra se cabe, se aperta ou se não cabe.
A12: 6. Na aba "Objetivos", cadastre sua reserva de emergência, viagens e gastos do ano.
A14: No iPhone
... A25: Criada e desenhada por Emerson Silva - DreamyStation. Obra protegida pela Lei de Direitos Autorais (Lei 9.610/1998): uso pessoal permitido; é proibido copiar, redistribuir, vender ou alterar sem autorização.

Sheet Resumo
A1: Resumo
A3: Saldo inicial (digite aqui) | B3: 1250
A4: SALDO HOJE | B4: =B3+SUMIFS('Lançamentos'!$H$2:$H$1001,'Lançamentos'!$F$2:$F$1001,"Já aconteceu") | C4: Saldo inicial + o que já aconteceu
A6: Até o fim deste mês
A7: + entradas que ainda vão acontecer | B7: =SUMIFS('Lançamentos'!$H$2:$H$1001,'Lançamentos'!$F$2:$F$1001,"Vai acontecer",'Lançamentos'!$H$2:$H$1001,">0",'Lançamentos'!$A$2:$A$1001,"<="&EOMONTH(TODAY(),0))
A8: − saídas que ainda vão acontecer (inclui atrasadas) | B8: =-SUMIFS('Lançamentos'!$H$2:$H$1001,'Lançamentos'!$F$2:$F$1001,"Vai acontecer",'Lançamentos'!$H$2:$H$1001,"<0",'Lançamentos'!$A$2:$A$1001,"<="&EOMONTH(TODAY(),0))
A9: − separado nos objetivos | B9: ='Objetivos'!C2
A10: SALDO LIVRE NO MÊS | B10: =B4+B7-B8-B9
A12: Dívidas e parcelas na renda
A13: Renda média por mês (digite aqui) | B13: 3000
A14: Dívidas e parcelas nos próximos 30 dias | B14: =-SUMIFS('Lançamentos'!$H$2:$H$1001,'Lançamentos'!$F$2:$F$1001,"Vai acontecer",'Lançamentos'!$E$2:$E$1001,"Dívidas",'Lançamentos'!$H$2:$H$1001,"<0",'Lançamentos'!$A$2:$A$1001,"<="&(TODAY()+30))
A15: Comprometimento da renda | B15: =IF(N(B13)>0,B14/B13,"") | C15: =IF(B15="","informe a renda",IF(B15>0.3,"Alto: acima de 30%",IF(B15>0.2,"Atenção","Tranquilo")))
A17: Mês para ver (qualquer dia dele) | B17: =TODAY()
A18: Entradas do mês | B18: =SUMIFS('Lançamentos'!$H$2:$H$1001,'Lançamentos'!$I$2:$I$1001,YEAR(B17)*100+MONTH(B17),'Lançamentos'!$F$2:$F$1001,"Já aconteceu",'Lançamentos'!$H$2:$H$1001,">0")
A19: Saídas do mês | B19: =-SUMIFS('Lançamentos'!$H$2:$H$1001,'Lançamentos'!$I$2:$I$1001,YEAR(B17)*100+MONTH(B17),'Lançamentos'!$F$2:$F$1001,"Já aconteceu",'Lançamentos'!$H$2:$H$1001,"<0")
A20: Sobrou no mês | B20: =B18-B19
A22: Saídas do mês por categoria
A23: Categoria | B23: Gasto | C23: % das saídas
A24: =Categorias!A2 | B24: =-SUMIFS('Lançamentos'!$H$2:$H$1001,'Lançamentos'!$D$2:$D$1001,A24,'Lançamentos'!$I$2:$I$1001,YEAR($B$17)*100+MONTH($B$17),'Lançamentos'!$F$2:$F$1001,"Já aconteceu",'Lançamentos'!$H$2:$H$1001,"<0") | C24: =IF($B$19>0,B24/$B$19,"")
A25: =Categorias!A3 | B25: =-SUMIFS('Lançamentos'!$H$2:$H$1001,'Lançamentos'!$D$2:$D$1001,A25,'Lançamentos'!$I$2:$I$1001,YEAR($B$17)*100+MONTH($B$17),'Lançamentos'!$F$2:$F$1001,"Já aconteceu",'Lançamentos'!$H$2:$H$1001,"<0") | C25: =IF($B$19>0,B25/$B$19,"")
A26: =Categorias!A4 | B26: =-SUMIFS('Lançamentos'!$H$2:$H$1001,'Lançamentos'!$D$2:$D$1001,A26,'Lançamentos'!$I$2:$I$1001,YEAR($B$17)*100+MONTH($B$17),'Lançamentos'!$F$2:$F$1001,"Já aconteceu",'Lançamentos'!$H$2:$H$1001,"<0") | C26: =IF($B$19>0,B26/$B$19,"")
A27: =Categorias!A5 | B27: =-SUMIFS('Lançamentos'!$H$2:$H$1001,'Lançamentos'!$D$2:$D$1001,A27,'Lançamentos'!$I$2:$I$1001,YEAR($B$17)*100+MONTH($B$17),'Lançamentos'!$F$2:$F$1001,"Já aconteceu",'Lançamentos'!$H$2:$H$1001,"<0") | C27: =IF($B$19>0,B27/$B$19,"")
A28: =Categorias!A6 | B28: =-SUMIFS('Lançamentos'!$H$2:$H$1001,'Lançamentos'!$D$2:$D$1001,A28,'Lançamentos'!$I$2:$I$1001,YEAR($B$17)*100+MONTH($B$17),'Lançamentos'!$F$2:$F$1001,"Já aconteceu",'Lançamentos'!$H$2:$H$1001,"<0") | C28: =IF($B$19>0,B28/$B$19,"")
A29: =Categorias!A7 | B29: =-SUMIFS('Lançamentos'!$H$2:$H$1001,'Lançamentos'!$D$2:$D$1001,A29,'Lançamentos'!$I$2:$I$1001,YEAR($B$17)*100+MONTH($B$17),'Lançamentos'!$F$2:$F$1001,"Já aconteceu",'Lançamentos'!$H$2:$H$1001,"<0") | C29: =IF($B$19>0,B29/$B$19,"")
A30: =Categorias!A8 | B30: =-SUMIFS('Lançamentos'!$H$2:$H$1001,'Lançamentos'!$D$2:$D$1001,A30,'Lançamentos'!$I$2:$I$1001,YEAR($B$17)*100+MONTH($B$17),'Lançamentos'!$F$2:$F$1001,"Já aconteceu",'Lançamentos'!$H$2:$H$1001,"<0") | C30: =IF($B$19>0,B30/$B$19,"")
A31: =Categorias!A9 | B31: =-SUMIFS('Lançamentos'!$H$2:$H$1001,'Lançamentos'!$D$2:$D$1001,A31,'Lançamentos'!$I$2:$I$1001,YEAR($B$17)*100+MONTH($B$17),'Lançamentos'!$F$2:$F$1001,"Já aconteceu",'Lançamentos'!$H$2:$H$1001,"<0") | C31: =IF($B$19>0,B31/$B$19,"")
A32: =Categorias!A10 | B32: =-SUMIFS('Lançamentos'!$H$2:$H$1001,'Lançamentos'!$D$2:$D$1001,A32,'Lançamentos'!$I$2:$I$1001,YEAR($B$17)*100+MONTH($B$17),'Lançamentos'!$F$2:$F$1001,"Já aconteceu",'Lançamentos'!$H$2:$H$1001,"<0") | C32: =IF($B$19>0,B32/$B$19,"")
A33: =Categorias!A11 | B33: =-SUMIFS('Lançamentos'!$H$2:$H$1001,'Lançamentos'!$D$2:$D$1001,A33,'Lançamentos'!$I$2:$I$1001,YEAR($B$17)*100+MONTH($B$17),'Lançamentos'!$F$2:$F$1001,"Já aconteceu",'Lançamentos'!$H$2:$H$1001,"<0") | C33: =IF($B$19>0,B33/$B$19,"")
A34: =Categorias!A12 | B34: =-SUMIFS('Lançamentos'!$H$2:$H$1001,'Lançamentos'!$D$2:$D$1001,A34,'Lançamentos'!$I$2:$I$1001,YEAR($B$17)*100+MONTH($B$17),'Lançamentos'!$F$2:$F$1001,"Já aconteceu",'Lançamentos'!$H$2:$H$1001,"<0") | C34: =IF($B$19>0,B34/$B$19,"")
A35: =Categorias!A13 | B35: =-SUMIFS('Lançamentos'!$H$2:$H$1001,'Lançamentos'!$D$2:$D$1001,A35,'Lançamentos'!$I$2:$I$1001,YEAR($B$17)*100+MONTH($B$17),'Lançamentos'!$F$2:$F$1001,"Já aconteceu",'Lançamentos'!$H$2:$H$1001,"<0") | C35: =IF($B$19>0,B35/$B$19,"")
A38: Saídas do mês por importância
A39: Importância | B39: Gasto | C39: % das saídas
A40: Essencial | B40: =-SUMIFS('Lançamentos'!$H$2:$H$1001,'Lançamentos'!$E$2:$E$1001,A40,'Lançamentos'!$I$2:$I$1001,YEAR($B$17)*100+MONTH($B$17),'Lançamentos'!$F$2:$F$1001,"Já aconteceu",'Lançamentos'!$H$2:$H$1001,"<0") | C40: =IF($B$19>0,B40/$B$19,"")
A41: Dívidas | B41: =-SUMIFS('Lançamentos'!$H$2:$H$1001,'Lançamentos'!$E$2:$E$1001,A41,'Lançamentos'!$I$2:$I$1001,YEAR($B$17)*100+MONTH($B$17),'Lançamentos'!$F$2:$F$1001,"Já aconteceu",'Lançamentos'!$H$2:$H$1001,"<0") | C41: =IF($B$19>0,B41/$B$19,"")
A42: Importante | B42: =-SUMIFS('Lançamentos'!$H$2:$H$1001,'Lançamentos'!$E$2:$E$1001,A42,'Lançamentos'!$I$2:$I$1001,YEAR($B$17)*100+MONTH($B$17),'Lançamentos'!$F$2:$F$1001,"Já aconteceu",'Lançamentos'!$H$2:$H$1001,"<0") | C42: =IF($B$19>0,B42/$B$19,"")
A43: Quero | B43: =-SUMIFS('Lançamentos'!$H$2:$H$1001,'Lançamentos'!$E$2:$E$1001,A43,'Lançamentos'!$I$2:$I$1001,YEAR($B$17)*100+MONTH($B$17),'Lançamentos'!$F$2:$F$1001,"Já aconteceu",'Lançamentos'!$H$2:$H$1001,"<0") | C43: =IF($B$19>0,B43/$B$19,"")

Sheet Lançamentos
A1: Data | B1: Tipo | C1: Valor | D1: Categoria | E1: Importância | F1: Situação | G1: Descrição | H1: Valor com sinal | I1: Mês | J1: Peso
A2: 46296 | B2: Entrada | C2: 3200 | D2: Salário | E2: Essencial | F2: Já aconteceu | G2: Salário (exemplo) | H2: =IF(OR(B2="",C2=""),0,IF(B2="Entrada",C2,-C2)) | I2: =IF(A2="","",YEAR(A2)*100+MONTH(A2)) | J2: =IF(E2="Essencial",1,IF(E2="Dívidas",2,IF(E2="Importante",3,IF(E2="Quero",4,""))))
A3: 46297 | B3: Saída | C3: 189.9 | D3: Mercado | E3: Essencial | F3: Já aconteceu | G3: Mercado (exemplo) | H3: =IF(OR(B3="",C3=""),0,IF(B3="Entrada",C3,-C3)) | I3: =IF(A3="","",YEAR(A3)*100+MONTH(A3)) | J3: =IF(E3="Essencial",1,IF(E3="Dívidas",2,IF(E3="Importante",3,IF(E3="Quero",4,""))))
A4: 46298 | B4: Saída | C4: 65 | D4: Transporte | E4: Essencial | F4: Já aconteceu | G4: Transporte (exemplo) | H4: =IF(OR(B4="",C4=""),0,IF(B4="Entrada",C4,-C4)) | I4: =IF(A4="","",YEAR(A4)*100+MONTH(A4)) | J4: =IF(E4="Essencial",1,IF(E4="Dívidas",2,IF(E4="Importante",3,IF(E4="Quero",4,""))))
A5: 46300 | B5: Saída | C5: 72 | D5: Lazer | E5: Quero | F5: Já aconteceu | G5: Pizza com amigos (exemplo) | H5: =IF(OR(B5="",C5=""),0,IF(B5="Entrada",C5,-C5)) | I5: =IF(A5="","",YEAR(A5)*100+MONTH(A5)) | J5: =IF(E5="Essencial",1,IF(E5="Dívidas",2,IF(E5="Importante",3,IF(E5="Quero",4,""))))
A6: 46304 | B6: Saída | C6: 240 | D6: Dívidas | E6: Dívidas | F6: Já aconteceu | G6: Cartão, parcela 2/6 (exemplo) | H6: =IF(OR(B6="",C6=""),0,IF(B6="Entrada",C6,-C6)) | I6: =IF(A6="","",YEAR(A6)*100+MONTH(A6)) | J6: =IF(E6="Essencial",1,IF(E6="Dívidas",2,IF(E6="Importante",3,IF(E6="Quero",4,""))))
A7: 46315 | B7: Saída | C7: 800 | D7: Moradia | E7: Essencial | F7: Vai acontecer | G7: Aluguel (exemplo) | H7: =IF(OR(B7="",C7=""),0,IF(B7="Entrada",C7,-C7)) | I7: =IF(A7="","",YEAR(A7)*100+MONTH(A7)) | J7: =IF(E7="Essencial",1,IF(E7="Dívidas",2,IF(E7="Importante",3,IF(E7="Quero",4,""))))
A8: 46317 | B8: Saída | C8: 320 | D8: Dívidas | E8: Dívidas | F8: Vai acontecer | G8: Empréstimo, parcela (exemplo) | H8: =IF(OR(B8="",C8=""),0,IF(B8="Entrada",C8,-C8)) | I8: =IF(A8="","",YEAR(A8)*100+MONTH(A8)) | J8: =IF(E8="Essencial",1,IF(E8="Dívidas",2,IF(E8="Importante",3,IF(E8="Quero",4,""))))
A9: 46320 | B9: Saída | C9: 119.9 | D9: Contas básicas | E9: Essencial | F9: Vai acontecer | G9: Internet (exemplo) | H9: =IF(OR(B9="",C9=""),0,IF(B9="Entrada",C9,-C9)) | I9: =IF(A9="","",YEAR(A9)*100+MONTH(A9)) | J9: =IF(E9="Essencial",1,IF(E9="Dívidas",2,IF(E9="Importante",3,IF(E9="Quero",4,""))))
A10: 46323 | B10: Entrada | C10: 3200 | D10: Salário | E10: Essencial | F10: Vai acontecer | G10: Salário (exemplo) | H10: =IF(OR(B10="",C10=""),0,IF(B10="Entrada",C10,-C10)) | I10: =IF(A10="","",YEAR(A10)*100+MONTH(A10)) | J10: =IF(E10="Essencial",1,IF(E10="Dívidas",2,IF(E10="Importante",3,IF(E10="Quero",4,""))))
A11: 46346 | B11: Saída | C11: 800 | D11: Moradia | E11: Essencial | F11: Vai acontecer | G11: Aluguel do mês que vem (exemplo) | H11: =IF(OR(B11="",C11=""),0,IF(B11="Entrada",C11,-C11)) | I11: =IF(A11="","",YEAR(A11)*100+MONTH(A11)) | J11: =IF(E11="Essencial",1,IF(E11="Dívidas",2,IF(E11="Importante",3,IF(E11="Quero",4,""))))
H12: =IF(OR(B12="",C12=""),0,IF(B12="Entrada",C12,-C12)) | I12: =IF(A12="","",YEAR(A12)*100+MONTH(A12)) | J12: =IF(E12="Essencial",1,IF(E12="Dívidas",2,IF(E12="Importante",3,IF(E12="Quero",4,""))))
H13: =IF(OR(B13="",C13=""),0,IF(B13="Entrada",C13,-C13)) | I13: =IF(A13="","",YEAR(A13)*100+MONTH(A13)) | J13: =IF(E13="Essencial",1,IF(E13="Dívidas",2,IF(E13="Importante",3,IF(E13="Quero",4,""))))
H14: =IF(OR(B14="",C14=""),0,IF(B14="Entrada",C14,-C14)) | I14: =IF(A14="","",YEAR(A14)*100+MONTH(A14)) | J14: =IF(E14="Essencial",1,IF(E14="Dívidas",2,IF(E14="Importante",3,IF(E14="Quero",4,""))))
H15: =IF(OR(B15="",C15=""),0,IF(B15="Entrada",C15,-C15)) | I15: =IF(A15="","",YEAR(A15)*100+MONTH(A15)) | J15: =IF(E15="Essencial",1,IF(E15="Dívidas",2,IF(E15="Importante",3,IF(E15="Quero",4,""))))
H16: =IF(OR(B16="",C16=""),0,IF(B16="Entrada",C16,-C16)) | I16: =IF(A16="","",YEAR(A16)*100+MONTH(A16)) | J16: =IF(E16="Essencial",1,IF(E16="Dívidas",2,IF(E16="Importante",3,IF(E16="Quero",4,""))))
H17: =IF(OR(B17="",C17=""),0,IF(B17="Entrada",C17,-C17)) | I17: =IF(A17="","",YEAR(A17)*100+MONTH(A17)) | J17: =IF(E17="Essencial",1,IF(E17="Dívidas",2,IF(E17="Importante",3,IF(E17="Quero",4,""))))
H18: =IF(OR(B18="",C18=""),0,IF(B18="Entrada",C18,-C18)) | I18: =IF(A18="","",YEAR(A18)*100+MONTH(A18)) | J18: =IF(E18="Essencial",1,IF(E18="Dívidas",2,IF(E18="Importante",3,IF(E18="Quero",4,""))))
H19: =IF(OR(B19="",C19=""),0,IF(B19="Entrada",C19,-C19)) | I19: =IF(A19="","",YEAR(A19)*100+MONTH(A19)) | J19: =IF(E19="Essencial",1,IF(E19="Dívidas",2,IF(E19="Importante",3,IF(E19="Quero",4,""))))
H20: =IF(OR(B20="",C20=""),0,IF(B20="Entrada",C20,-C20)) | I20: =IF(A20="","",YEAR(A20)*100+MONTH(A20)) | J20: =IF(E20="Essencial",1,IF(E20="Dívidas",2,IF(E20="Importante",3,IF(E20="Quero",4,""))))
H21: =IF(OR(B21="",C21=""),0,IF(B21="Entrada",C21,-C21)) | I21: =IF(A21="","",YEAR(A21)*100+MONTH(A21)) | J21: =IF(E21="Essencial",1,IF(E21="Dívidas",2,IF(E21="Importante",3,IF(E21="Quero",4,""))))
H22: =IF(OR(B22="",C22=""),0,IF(B22="Entrada",C22,-C22)) | I22: =IF(A22="","",YEAR(A22)*100+MONTH(A22)) | J22: =IF(E22="Essencial",1,IF(E22="Dívidas",2,IF(E22="Importante",3,IF(E22="Quero",4,""))))
H23: =IF(OR(B23="",C23=""),0,IF(B23="Entrada",C23,-C23)) | I23: =IF(A23="","",YEAR(A23)*100+MONTH(A23)) | J23: =IF(E23="Essencial",1,IF(E23="Dívidas",2,IF(E23="Importante",3,IF(E23="Quero",4,""))))
... H1001: =IF(OR(B1001="",C1001=""),0,IF(B1001="Entrada",C1001,-C1001)) | I1001: =IF(A1001="","",YEAR(A1001)*100+MONTH(A1001)) | J1001: =IF(E1001="Essencial",1,IF(E1001="Dívidas",2,IF(E1001="Importante",3,IF(E1001="Quero",4,""))))

Sheet A pagar
A1: A pagar: em que ordem?
A2: Primeiro o essencial, depois dívidas, o importante e o que você quer. Dentro de cada grupo, o que vence antes.
A3: Total a pagar (atrasadas e futuras) | C3: =-SUMIFS('Lançamentos'!$H$2:$H$1001,'Lançamentos'!$F$2:$F$1001,"Vai acontecer",'Lançamentos'!$H$2:$H$1001,"<0")
A4: Seu saldo hoje | C4: =Resumo!B4
A6: Vencimento | B6: Descrição | C6: Valor | D6: Importância | E6: Peso | F6: Acumulado | G6: O saldo de hoje cobre? | H6: Faltaria | J6: As colunas A a E são preenchidas sozinhas a partir da aba Lançamentos (precisa do Google Planilhas).
A7: =IFERROR(SORT(FILTER({'Lançamentos'!$A$2:$A$1001,'Lançamentos'!$G$2:$G$1001,'Lançamentos'!$C$2:$C$1001,'Lançamentos'!$E$2:$E$1001,'Lançamentos'!$J$2:$J$1001},'Lançamentos'!$B$2:$B$1001="Saída",'Lançamentos'!$F$2:$F$1001="Vai acontecer"),5,TRUE,1,TRUE),"Nada a pagar") | F7: =IF(C7="","",SUM(C$7:C7)) | G7: =IF(C7="","",IF(F7<=$C$4,"Sim","Não")) | H7: =IF(C7="","",MAX(0,F7-$C$4))
F8: =IF(C8="","",SUM(C$7:C8)) | G8: =IF(C8="","",IF(F8<=$C$4,"Sim","Não")) | H8: =IF(C8="","",MAX(0,F8-$C$4))
F9: =IF(C9="","",SUM(C$7:C9)) | G9: =IF(C9="","",IF(F9<=$C$4,"Sim","Não")) | H9: =IF(C9="","",MAX(0,F9-$C$4))
F10: =IF(C10="","",SUM(C$7:C10)) | G10: =IF(C10="","",IF(F10<=$C$4,"Sim","Não")) | H10: =IF(C10="","",MAX(0,F10-$C$4))
F11: =IF(C11="","",SUM(C$7:C11)) | G11: =IF(C11="","",IF(F11<=$C$4,"Sim","Não")) | H11: =IF(C11="","",MAX(0,F11-$C$4))
F12: =IF(C12="","",SUM(C$7:C12)) | G12: =IF(C12="","",IF(F12<=$C$4,"Sim","Não")) | H12: =IF(C12="","",MAX(0,F12-$C$4))
F13: =IF(C13="","",SUM(C$7:C13)) | G13: =IF(C13="","",IF(F13<=$C$4,"Sim","Não")) | H13: =IF(C13="","",MAX(0,F13-$C$4))
F14: =IF(C14="","",SUM(C$7:C14)) | G14: =IF(C14="","",IF(F14<=$C$4,"Sim","Não")) | H14: =IF(C14="","",MAX(0,F14-$C$4))
F15: =IF(C15="","",SUM(C$7:C15)) | G15: =IF(C15="","",IF(F15<=$C$4,"Sim","Não")) | H15: =IF(C15="","",MAX(0,F15-$C$4))
F16: =IF(C16="","",SUM(C$7:C16)) | G16: =IF(C16="","",IF(F16<=$C$4,"Sim","Não")) | H16: =IF(C16="","",MAX(0,F16-$C$4))
F17: =IF(C17="","",SUM(C$7:C17)) | G17: =IF(C17="","",IF(F17<=$C$4,"Sim","Não")) | H17: =IF(C17="","",MAX(0,F17-$C$4))
F18: =IF(C18="","",SUM(C$7:C18)) | G18: =IF(C18="","",IF(F18<=$C$4,"Sim","Não")) | H18: =IF(C18="","",MAX(0,F18-$C$4))
F19: =IF(C19="","",SUM(C$7:C19)) | G19: =IF(C19="","",IF(F19<=$C$4,"Sim","Não")) | H19: =IF(C19="","",MAX(0,F19-$C$4))
... F206: =IF(C206="","",SUM(C$7:C206)) | G206: =IF(C206="","",IF(F206<=$C$4,"Sim","Não")) | H206: =IF(C206="","",MAX(0,F206-$C$4))

Sheet Simulador
A1: E se eu comprar?
A2: Nada é gravado: é só uma conta para decidir antes de gastar.
A3: Quanto custa? | B3: 0
A4: Como vai pagar? | B4: Parcelado
A5: Entrada, paga hoje (se parcelado) | B5: 0
A6: Número de parcelas | B6: 6
A7: Juros ao mês (digite com %, ex.: 3%) | B7: 0
A8: Folga mínima que você quer manter | B8: 100
A10: Valor de cada parcela | B10: =IF(OR(B4="À vista",B6<1),0,IF(B7=0,(B3-B5)/B6,PMT(B7,B6,-(B3-B5))))
A11: Total que sai do bolso | B11: =IF(B4="À vista",B3,B5+B10*B6)
A12: Juros pagos | B12: =MAX(0,B11-B3)
A13: VEREDITO | B13: =IF(B3<=0,"Digite o preço",IF(MIN(C17:C28)<0,"Não cabe agora",IF(MIN(C17:C28)<B8,"Dá, mas fica apertado","Cabe no seu orçamento")))
A16: Fim do mês | B16: Saldo sem a compra | C16: Saldo com a compra | E16: A entrada sai hoje; a 1ª parcela vence no mês que vem.
A17: =EOMONTH(TODAY(),0) | B17: =Resumo!$B$4+SUMIFS('Lançamentos'!$H$2:$H$1001,'Lançamentos'!$F$2:$F$1001,"Vai acontecer",'Lançamentos'!$A$2:$A$1001,"<="&A17) | C17: =B17-IF($B$4="À vista",$B$3,$B$5+$B$10*MIN(0,$B$6))
A18: =EOMONTH(TODAY(),1) | B18: =Resumo!$B$4+SUMIFS('Lançamentos'!$H$2:$H$1001,'Lançamentos'!$F$2:$F$1001,"Vai acontecer",'Lançamentos'!$A$2:$A$1001,"<="&A18) | C18: =B18-IF($B$4="À vista",$B$3,$B$5+$B$10*MIN(1,$B$6))
A19: =EOMONTH(TODAY(),2) | B19: =Resumo!$B$4+SUMIFS('Lançamentos'!$H$2:$H$1001,'Lançamentos'!$F$2:$F$1001,"Vai acontecer",'Lançamentos'!$A$2:$A$1001,"<="&A19) | C19: =B19-IF($B$4="À vista",$B$3,$B$5+$B$10*MIN(2,$B$6))
A20: =EOMONTH(TODAY(),3) | B20: =Resumo!$B$4+SUMIFS('Lançamentos'!$H$2:$H$1001,'Lançamentos'!$F$2:$F$1001,"Vai acontecer",'Lançamentos'!$A$2:$A$1001,"<="&A20) | C20: =B20-IF($B$4="À vista",$B$3,$B$5+$B$10*MIN(3,$B$6))
A21: =EOMONTH(TODAY(),4) | B21: =Resumo!$B$4+SUMIFS('Lançamentos'!$H$2:$H$1001,'Lançamentos'!$F$2:$F$1001,"Vai acontecer",'Lançamentos'!$A$2:$A$1001,"<="&A21) | C21: =B21-IF($B$4="À vista",$B$3,$B$5+$B$10*MIN(4,$B$6))
A22: =EOMONTH(TODAY(),5) | B22: =Resumo!$B$4+SUMIFS('Lançamentos'!$H$2:$H$1001,'Lançamentos'!$F$2:$F$1001,"Vai acontecer",'Lançamentos'!$A$2:$A$1001,"<="&A22) | C22: =B22-IF($B$4="À vista",$B$3,$B$5+$B$10*MIN(5,$B$6))
A23: =EOMONTH(TODAY(),6) | B23: =Resumo!$B$4+SUMIFS('Lançamentos'!$H$2:$H$1001,'Lançamentos'!$F$2:$F$1001,"Vai acontecer",'Lançamentos'!$A$2:$A$1001,"<="&A23) | C23: =B23-IF($B$4="À vista",$B$3,$B$5+$B$10*MIN(6,$B$6))
A24: =EOMONTH(TODAY(),7) | B24: =Resumo!$B$4+SUMIFS('Lançamentos'!$H$2:$H$1001,'Lançamentos'!$F$2:$F$1001,"Vai acontecer",'Lançamentos'!$A$2:$A$1001,"<="&A24) | C24: =B24-IF($B$4="À vista",$B$3,$B$5+$B$10*MIN(7,$B$6))
A25: =EOMONTH(TODAY(),8) | B25: =Resumo!$B$4+SUMIFS('Lançamentos'!$H$2:$H$1001,'Lançamentos'!$F$2:$F$1001,"Vai acontecer",'Lançamentos'!$A$2:$A$1001,"<="&A25) | C25: =B25-IF($B$4="À vista",$B$3,$B$5+$B$10*MIN(8,$B$6))
A26: =EOMONTH(TODAY(),9) | B26: =Resumo!$B$4+SUMIFS('Lançamentos'!$H$2:$H$1001,'Lançamentos'!$F$2:$F$1001,"Vai acontecer",'Lançamentos'!$A$2:$A$1001,"<="&A26) | C26: =B26-IF($B$4="À vista",$B$3,$B$5+$B$10*MIN(9,$B$6))
A27: =EOMONTH(TODAY(),10) | B27: =Resumo!$B$4+SUMIFS('Lançamentos'!$H$2:$H$1001,'Lançamentos'!$F$2:$F$1001,"Vai acontecer",'Lançamentos'!$A$2:$A$1001,"<="&A27) | C27: =B27-IF($B$4="À vista",$B$3,$B$5+$B$10*MIN(10,$B$6))
A28: =EOMONTH(TODAY(),11) | B28: =Resumo!$B$4+SUMIFS('Lançamentos'!$H$2:$H$1001,'Lançamentos'!$F$2:$F$1001,"Vai acontecer",'Lançamentos'!$A$2:$A$1001,"<="&A28) | C28: =B28-IF($B$4="À vista",$B$3,$B$5+$B$10*MIN(11,$B$6))

Sheet Objetivos
A1: Objetivos
A2: Total separado nos objetivos | C2: =SUM(C5:C34) | D2: O dinheiro continua no saldo, mas sai do "saldo livre".
A4: Nome | B4: Meta | C4: Guardado | D4: Prazo | E4: Falta | F4: Progresso | G4: Por mês até o prazo
A5: Reserva de emergência (exemplo) | B5: 9000 | C5: 2500 | D5: 46661 | E5: =IF(B5="","",MAX(0,B5-C5)) | F5: =IF(B5>0,MIN(1,C5/B5),"") | G5: =IF(OR(B5="",D5="",E5=0),"",IFERROR(ROUNDUP(E5/MAX(1,DATEDIF(TODAY(),D5,"M")),2),"prazo passou"))
A6: Viagem de fim de ano (exemplo) | B6: 4000 | C6: 800 | D6: 46357 | E6: =IF(B6="","",MAX(0,B6-C6)) | F6: =IF(B6>0,MIN(1,C6/B6),"") | G6: =IF(OR(B6="",D6="",E6=0),"",IFERROR(ROUNDUP(E6/MAX(1,DATEDIF(TODAY(),D6,"M")),2),"prazo passou"))
E7: =IF(B7="","",MAX(0,B7-C7)) | F7: =IF(B7>0,MIN(1,C7/B7),"") | G7: =IF(OR(B7="",D7="",E7=0),"",IFERROR(ROUNDUP(E7/MAX(1,DATEDIF(TODAY(),D7,"M")),2),"prazo passou"))
E8: =IF(B8="","",MAX(0,B8-C8)) | F8: =IF(B8>0,MIN(1,C8/B8),"") | G8: =IF(OR(B8="",D8="",E8=0),"",IFERROR(ROUNDUP(E8/MAX(1,DATEDIF(TODAY(),D8,"M")),2),"prazo passou"))
E9: =IF(B9="","",MAX(0,B9-C9)) | F9: =IF(B9>0,MIN(1,C9/B9),"") | G9: =IF(OR(B9="",D9="",E9=0),"",IFERROR(ROUNDUP(E9/MAX(1,DATEDIF(TODAY(),D9,"M")),2),"prazo passou"))
E10: =IF(B10="","",MAX(0,B10-C10)) | F10: =IF(B10>0,MIN(1,C10/B10),"") | G10: =IF(OR(B10="",D10="",E10=0),"",IFERROR(ROUNDUP(E10/MAX(1,DATEDIF(TODAY(),D10,"M")),2),"prazo passou"))
E11: =IF(B11="","",MAX(0,B11-C11)) | F11: =IF(B11>0,MIN(1,C11/B11),"") | G11: =IF(OR(B11="",D11="",E11=0),"",IFERROR(ROUNDUP(E11/MAX(1,DATEDIF(TODAY(),D11,"M")),2),"prazo passou"))
E12: =IF(B12="","",MAX(0,B12-C12)) | F12: =IF(B12>0,MIN(1,C12/B12),"") | G12: =IF(OR(B12="",D12="",E12=0),"",IFERROR(ROUNDUP(E12/MAX(1,DATEDIF(TODAY(),D12,"M")),2),"prazo passou"))
E13: =IF(B13="","",MAX(0,B13-C13)) | F13: =IF(B13>0,MIN(1,C13/B13),"") | G13: =IF(OR(B13="",D13="",E13=0),"",IFERROR(ROUNDUP(E13/MAX(1,DATEDIF(TODAY(),D13,"M")),2),"prazo passou"))
E14: =IF(B14="","",MAX(0,B14-C14)) | F14: =IF(B14>0,MIN(1,C14/B14),"") | G14: =IF(OR(B14="",D14="",E14=0),"",IFERROR(ROUNDUP(E14/MAX(1,DATEDIF(TODAY(),D14,"M")),2),"prazo passou"))
E15: =IF(B15="","",MAX(0,B15-C15)) | F15: =IF(B15>0,MIN(1,C15/B15),"") | G15: =IF(OR(B15="",D15="",E15=0),"",IFERROR(ROUNDUP(E15/MAX(1,DATEDIF(TODAY(),D15,"M")),2),"prazo passou"))
E16: =IF(B16="","",MAX(0,B16-C16)) | F16: =IF(B16>0,MIN(1,C16/B16),"") | G16: =IF(OR(B16="",D16="",E16=0),"",IFERROR(ROUNDUP(E16/MAX(1,DATEDIF(TODAY(),D16,"M")),2),"prazo passou"))
E17: =IF(B17="","",MAX(0,B17-C17)) | F17: =IF(B17>0,MIN(1,C17/B17),"") | G17: =IF(OR(B17="",D17="",E17=0),"",IFERROR(ROUNDUP(E17/MAX(1,DATEDIF(TODAY(),D17,"M")),2),"prazo passou"))
E18: =IF(B18="","",MAX(0,B18-C18)) | F18: =IF(B18>0,MIN(1,C18/B18),"") | G18: =IF(OR(B18="",D18="",E18=0),"",IFERROR(ROUNDUP(E18/MAX(1,DATEDIF(TODAY(),D18,"M")),2),"prazo passou"))
... E34: =IF(B34="","",MAX(0,B34-C34)) | F34: =IF(B34>0,MIN(1,C34/B34),"") | G34: =IF(OR(B34="",D34="",E34=0),"",IFERROR(ROUNDUP(E34/MAX(1,DATEDIF(TODAY(),D34,"M")),2),"prazo passou"))

Sheet Categorias
A1: Categoria | B1: Importância padrão | D1: Dica: pode acrescentar categorias no fim da lista.
A2: Moradia | B2: Essencial
A3: Mercado | B3: Essencial
A4: Saúde | B4: Essencial
A5: Contas básicas | B5: Essencial
A6: Transporte | B6: Essencial
A7: Dívidas | B7: Dívidas
A8: Estudos | B8: Importante
A9: Trabalho | B9: Importante
A10: Lazer | B10: Quero
A11: Compras | B11: Quero
A12: Salário | B12: Essencial
A13: Outros | B13: Importante
